README.txt
setup.py
torweb/__init__.py
torweb/cache.py
torweb/command.py
torweb/config.py
torweb/datastructure.py
torweb/db.py
torweb/handlers.py
torweb/paginator.py
torweb/run_torweb.py
torweb/script.py
torweb/sessions.py
torweb/soaphandler.py
torweb/tmpl.py
torweb/urls.py
torweb/wrappers.py
torweb.egg-info/PKG-INFO
torweb.egg-info/SOURCES.txt
torweb.egg-info/dependency_links.txt
torweb.egg-info/top_level.txt
torweb/lib/__init__.py
torweb/lib/soaplib/__init__.py
torweb/lib/soaplib/client.py
torweb/lib/soaplib/easy_client.py
torweb/lib/soaplib/etimport.py
torweb/lib/soaplib/service.py
torweb/lib/soaplib/soap.py
torweb/lib/soaplib/util.py
torweb/lib/soaplib/wsgi.py
torweb/lib/soaplib/wsgi_soap.py
torweb/lib/soaplib/xml.py
torweb/lib/soaplib/ext/__init__.py
torweb/lib/soaplib/ext/comproxy.py
torweb/lib/soaplib/ext/wsdl2py.py
torweb/lib/soaplib/serializers/__init__.py
torweb/lib/soaplib/serializers/base.py
torweb/lib/soaplib/serializers/binary.py
torweb/lib/soaplib/serializers/clazz.py
torweb/lib/soaplib/serializers/enum.py
torweb/lib/soaplib/serializers/exception.py
torweb/lib/soaplib/serializers/primitive.py
torweb/lib/soaplib/serializers/table.py
torweb/lib/soaplib/util/__init__.py
torweb/lib/soaplib/util/duration.py
torweb/lib/soaplib/util/etreeconv.py
torweb/lib/soaplib/util/odict.py
torweb/lib/soaplib/util/server.py
torweb/utils/__init__.py
torweb/utils/imagecaptcha.py
torweb/utils/memcache.py
torweb/utils/pyDes.py
torweb/utils/start_app.py