Metadata-Version: 1.0
Name: torweb
Version: 0.0.16
Summary: torweb
Home-page: UNKNOWN
Author: zhangpeng
Author-email: zhangpeng1@infohold.com.cn
License: UNKNOWN
Platform: UNKNOWN
